{
  "showdown_name": "Rotom-Frost",
  "form_text": "Frost Rotom",
  "personal_id": "0479003",
  "national_dex": 479,
  "form_index": 3,
  "sex": 2,
  "reg_no": 1,
  "merge_fo": 3,
  "ff": "14",
  "types": [
    "Electric",
    "Ice"
  ],
  "stats": {
    "hp": 50,
    "atk": 65,
    "def": 107,
    "spa": 105,
    "spd": 107,
    "spe": 86
  },
  "abilities": [
    {
      "slot": 0,
      "id": 26,
      "name": "Levitate",
      "description": "The Pokémon floats off the ground, making it immune to\nGround-type moves, as well as the Spikes, Toxic Spikes,\nand Sticky Web statuses."
    }
  ],
  "hidden_ability": null,
  "weight_hg": 3,
  "is_valid": true,
  "learnset": [
    {
      "id": 59,
      "name": "Blizzard",
      "showdown_id": "blizzard",
      "type": "Ice",
      "category": "special",
      "power": 110,
      "accuracy": 70,
      "pp": 8,
      "priority": 0,
      "target": "all-opponents"
    },
    {
      "id": 84,
      "name": "Thunder Shock",
      "showdown_id": "thundershock",
      "type": "Electric",
      "category": "special",
      "power": 40,
      "accuracy": 100,
      "pp": 20,
      "priority": 0,
      "target": "selected"
    },
    {
      "id": 85,
      "name": "Thunderbolt",
      "showdown_id": "thunderbolt",
      "type": "Electric",
      "category": "special",
      "power": 90,
      "accuracy": 100,
      "pp": 16,
      "priority": 0,
      "target": "selected"
    },
    {
      "id": 86,
      "name": "Thunder Wave",
      "showdown_id": "thunderwave",
      "type": "Electric",
      "category": "status",
      "power": 0,
      "accuracy": 90,
      "pp": 20,
      "priority": 0,
      "target": "selected"
    },
    {
      "id": 87,
      "name": "Thunder",
      "showdown_id": "thunder",
      "type": "Electric",
      "category": "special",
      "power": 110,
      "accuracy": 70,
      "pp": 12,
      "priority": 0,
      "target": "selected"
    },
    {
      "id": 101,
      "name": "Night Shade",
      "showdown_id": "nightshade",
      "type": "Ghost",
      "category": "special",
      "power": 1,
      "accuracy": 100,
      "pp": 16,
      "priority": 0,
      "target": "selected"
    },
    {
      "id": 104,
      "name": "Double Team",
      "showdown_id": "doubleteam",
      "type": "Normal",
      "category": "status",
      "power": 0,
      "accuracy": 101,
      "pp": 16,
      "priority": 0,
      "target": "user-side"
    },
    {
      "id": 109,
      "name": "Confuse Ray",
      "showdown_id": "confuseray",
      "type": "Ghost",
      "category": "status",
      "power": 0,
      "accuracy": 100,
      "pp": 12,
      "priority": 0,
      "target": "selected"
    },
    {
      "id": 113,
      "name": "Light Screen",
      "showdown_id": "lightscreen",
      "type": "Psychic",
      "category": "status",
      "power": 0,
      "accuracy": 101,
      "pp": 20,
      "priority": 0,
      "target": "raw(12)"
    },
    {
      "id": 115,
      "name": "Reflect",
      "showdown_id": "reflect",
      "type": "Psychic",
      "category": "status",
      "power": 0,
      "accuracy": 101,
      "pp": 20,
      "priority": 0,
      "target": "raw(12)"
    },
    {
      "id": 156,
      "name": "Rest",
      "showdown_id": "rest",
      "type": "Psychic",
      "category": "status",
      "power": 0,
      "accuracy": 101,
      "pp": 8,
      "priority": 0,
      "target": "user-side"
    },
    {
      "id": 164,
      "name": "Substitute",
      "showdown_id": "substitute",
      "type": "Normal",
      "category": "status",
      "power": 0,
      "accuracy": 101,
      "pp": 12,
      "priority": 0,
      "target": "user-side"
    },
    {
      "id": 168,
      "name": "Thief",
      "showdown_id": "thief",
      "type": "Dark",
      "category": "physical",
      "power": 60,
      "accuracy": 100,
      "pp": 20,
      "priority": 0,
      "target": "selected"
    },
    {
      "id": 173,
      "name": "Snore",
      "showdown_id": "snore",
      "type": "Normal",
      "category": "special",
      "power": 50,
      "accuracy": 100,
      "pp": 16,
      "priority": 0,
      "target": "selected"
    },
    {
      "id": 180,
      "name": "Spite",
      "showdown_id": "spite",
      "type": "Ghost",
      "category": "status",
      "power": 0,
      "accuracy": 100,
      "pp": 12,
      "priority": 0,
      "target": "selected"
    },
    {
      "id": 182,
      "name": "Protect",
      "showdown_id": "protect",
      "type": "Normal",
      "category": "status",
      "power": 0,
      "accuracy": 101,
      "pp": 8,
      "priority": 4,
      "target": "user-side"
    },
    {
      "id": 203,
      "name": "Endure",
      "showdown_id": "endure",
      "type": "Normal",
      "category": "status",
      "power": 0,
      "accuracy": 101,
      "pp": 12,
      "priority": 4,
      "target": "user-side"
    },
    {
      "id": 214,
      "name": "Sleep Talk",
      "showdown_id": "sleeptalk",
      "type": "Normal",
      "category": "status",
      "power": 0,
      "accuracy": 101,
      "pp": 12,
      "priority": 0,
      "target": "user-side"
    },
    {
      "id": 220,
      "name": "Pain Split",
      "showdown_id": "painsplit",
      "type": "Normal",
      "category": "status",
      "power": 0,
      "accuracy": 101,
      "pp": 20,
      "priority": 0,
      "target": "selected"
    },
    {
      "id": 240,
      "name": "Rain Dance",
      "showdown_id": "raindance",
      "type": "Water",
      "category": "status",
      "power": 0,
      "accuracy": 101,
      "pp": 8,
      "priority": 0,
      "target": "any"
    },
    {
      "id": 241,
      "name": "Sunny Day",
      "showdown_id": "sunnyday",
      "type": "Fire",
      "category": "status",
      "power": 0,
      "accuracy": 101,
      "pp": 8,
      "priority": 0,
      "target": "any"
    },
    {
      "id": 247,
      "name": "Shadow Ball",
      "showdown_id": "shadowball",
      "type": "Ghost",
      "category": "special",
      "power": 80,
      "accuracy": 100,
      "pp": 16,
      "priority": 0,
      "target": "selected"
    },
    {
      "id": 253,
      "name": "Uproar",
      "showdown_id": "uproar",
      "type": "Normal",
      "category": "special",
      "power": 90,
      "accuracy": 100,
      "pp": 12,
      "priority": 0,
      "target": "field"
    },
    {
      "id": 261,
      "name": "Will-O-Wisp",
      "showdown_id": "willowisp",
      "type": "Fire",
      "category": "status",
      "power": 0,
      "accuracy": 85,
      "pp": 16,
      "priority": 0,
      "target": "selected"
    },
    {
      "id": 263,
      "name": "Facade",
      "showdown_id": "facade",
      "type": "Normal",
      "category": "physical",
      "power": 70,
      "accuracy": 100,
      "pp": 20,
      "priority": 0,
      "target": "selected"
    },
    {
      "id": 268,
      "name": "Charge",
      "showdown_id": "charge",
      "type": "Electric",
      "category": "status",
      "power": 0,
      "accuracy": 101,
      "pp": 20,
      "priority": 0,
      "target": "user-side"
    },
    {
      "id": 270,
      "name": "Helping Hand",
      "showdown_id": "helpinghand",
      "type": "Normal",
      "category": "status",
      "power": 0,
      "accuracy": 101,
      "pp": 20,
      "priority": 5,
      "target": "ally"
    },
    {
      "id": 271,
      "name": "Trick",
      "showdown_id": "trick",
      "type": "Psychic",
      "category": "status",
      "power": 0,
      "accuracy": 100,
      "pp": 12,
      "priority": 0,
      "target": "selected"
    },
    {
      "id": 304,
      "name": "Hyper Voice",
      "showdown_id": "hypervoice",
      "type": "Normal",
      "category": "special",
      "power": 90,
      "accuracy": 100,
      "pp": 12,
      "priority": 0,
      "target": "all-opponents"
    },
    {
      "id": 399,
      "name": "Dark Pulse",
      "showdown_id": "darkpulse",
      "type": "Dark",
      "category": "special",
      "power": 80,
      "accuracy": 100,
      "pp": 16,
      "priority": 0,
      "target": "selected"
    },
    {
      "id": 417,
      "name": "Nasty Plot",
      "showdown_id": "nastyplot",
      "type": "Dark",
      "category": "status",
      "power": 0,
      "accuracy": 101,
      "pp": 20,
      "priority": 0,
      "target": "user-side"
    },
    {
      "id": 435,
      "name": "Discharge",
      "showdown_id": "discharge",
      "type": "Electric",
      "category": "special",
      "power": 80,
      "accuracy": 100,
      "pp": 16,
      "priority": 0,
      "target": "all-other-pokemon"
    },
    {
      "id": 451,
      "name": "Charge Beam",
      "showdown_id": "chargebeam",
      "type": "Electric",
      "category": "special",
      "power": 50,
      "accuracy": 90,
      "pp": 12,
      "priority": 0,
      "target": "selected"
    },
    {
      "id": 486,
      "name": "Electro Ball",
      "showdown_id": "electroball",
      "type": "Electric",
      "category": "special",
      "power": 1,
      "accuracy": 100,
      "pp": 12,
      "priority": 0,
      "target": "selected"
    },
    {
      "id": 492,
      "name": "Foul Play",
      "showdown_id": "foulplay",
      "type": "Dark",
      "category": "physical",
      "power": 95,
      "accuracy": 100,
      "pp": 16,
      "priority": 0,
      "target": "selected"
    },
    {
      "id": 496,
      "name": "Round",
      "showdown_id": "round",
      "type": "Normal",
      "category": "special",
      "power": 60,
      "accuracy": 100,
      "pp": 16,
      "priority": 0,
      "target": "selected"
    },
    {
      "id": 500,
      "name": "Stored Power",
      "showdown_id": "storedpower",
      "type": "Psychic",
      "category": "special",
      "power": 20,
      "accuracy": 100,
      "pp": 12,
      "priority": 0,
      "target": "selected"
    },
    {
      "id": 506,
      "name": "Hex",
      "showdown_id": "hex",
      "type": "Ghost",
      "category": "special",
      "power": 65,
      "accuracy": 100,
      "pp": 12,
      "priority": 0,
      "target": "selected"
    },
    {
      "id": 521,
      "name": "Volt Switch",
      "showdown_id": "voltswitch",
      "type": "Electric",
      "category": "special",
      "power": 70,
      "accuracy": 100,
      "pp": 20,
      "priority": 0,
      "target": "selected"
    },
    {
      "id": 527,
      "name": "Electroweb",
      "showdown_id": "electroweb",
      "type": "Electric",
      "category": "special",
      "power": 55,
      "accuracy": 95,
      "pp": 16,
      "priority": 0,
      "target": "all-opponents"
    },
    {
      "id": 598,
      "name": "Eerie Impulse",
      "showdown_id": "eerieimpulse",
      "type": "Electric",
      "category": "status",
      "power": 0,
      "accuracy": 100,
      "pp": 16,
      "priority": 0,
      "target": "selected"
    },
    {
      "id": 604,
      "name": "Electric Terrain",
      "showdown_id": "electricterrain",
      "type": "Electric",
      "category": "status",
      "power": 0,
      "accuracy": 101,
      "pp": 12,
      "priority": 0,
      "target": "any"
    },
    {
      "id": 804,
      "name": "Rising Voltage",
      "showdown_id": "risingvoltage",
      "type": "Electric",
      "category": "special",
      "power": 70,
      "accuracy": 100,
      "pp": 20,
      "priority": 0,
      "target": "selected"
    },
    {
      "id": 809,
      "name": "Poltergeist",
      "showdown_id": "poltergeist",
      "type": "Ghost",
      "category": "physical",
      "power": 110,
      "accuracy": 90,
      "pp": 8,
      "priority": 0,
      "target": "selected"
    }
  ],
  "usage": {
    "present": true,
    "by_cutoff": {
      "0": {
        "usage": 0.0033761000000000004,
        "raw_count": 8844,
        "viability_ceiling": [
          964,
          74,
          69,
          58
        ],
        "top_items": [
          {
            "key": "choicescarf",
            "weight": 5083.0
          },
          {
            "key": "nevermeltice",
            "weight": 771.0
          },
          {
            "key": "sitrusberry",
            "weight": 729.0
          },
          {
            "key": "leftovers",
            "weight": 567.0
          },
          {
            "key": "lifeorb",
            "weight": 452.0
          },
          {
            "key": "focussash",
            "weight": 290.0
          },
          {
            "key": "magnet",
            "weight": 240.0
          },
          {
            "key": "widelens",
            "weight": 233.0
          }
        ],
        "top_moves": [
          {
            "key": "blizzard",
            "weight": 8730.0
          },
          {
            "key": "voltswitch",
            "weight": 5494.0
          },
          {
            "key": "thunderbolt",
            "weight": 4357.0
          },
          {
            "key": "electroweb",
            "weight": 3484.0
          },
          {
            "key": "discharge",
            "weight": 2823.0
          },
          {
            "key": "protect",
            "weight": 2489.0
          },
          {
            "key": "willowisp",
            "weight": 2207.0
          },
          {
            "key": "trick",
            "weight": 1759.0
          }
        ],
        "top_abilities": [
          {
            "key": "levitate",
            "weight": 8844.0
          }
        ],
        "top_spreads": [
          {
            "key": "Timid:2/0/0/32/0/32",
            "weight": 3811.0
          },
          {
            "key": "Modest:2/0/0/32/0/32",
            "weight": 781.0
          },
          {
            "key": "Timid:0/0/0/32/2/32",
            "weight": 363.0
          },
          {
            "key": "Calm:32/0/0/2/32/0",
            "weight": 272.0
          },
          {
            "key": "Modest:32/0/0/32/2/0",
            "weight": 244.0
          },
          {
            "key": "Modest:0/0/2/32/0/32",
            "weight": 209.0
          },
          {
            "key": "Modest:32/0/0/32/0/2",
            "weight": 183.0
          },
          {
            "key": "Timid:32/0/0/2/0/32",
            "weight": 148.0
          }
        ],
        "top_teammates": [
          {
            "key": "Froslass-Mega",
            "weight": 4357.0
          },
          {
            "key": "Garchomp",
            "weight": 3384.0
          },
          {
            "key": "Incineroar",
            "weight": 2126.0
          },
          {
            "key": "Kingambit",
            "weight": 1791.0
          },
          {
            "key": "Sneasler",
            "weight": 1483.0
          },
          {
            "key": "Ninetales-Alola",
            "weight": 1469.0
          },
          {
            "key": "Basculegion",
            "weight": 1226.0
          },
          {
            "key": "Whimsicott",
            "weight": 1205.0
          }
        ],
        "top_counters": [
          {
            "key": "Torkoal",
            "score": 0.5735,
            "n": 136
          },
          {
            "key": "Charizard-Mega-Y",
            "score": 0.56,
            "n": 175
          },
          {
            "key": "Tyranitar-Mega",
            "score": 0.5577,
            "n": 52
          },
          {
            "key": "Mawile-Mega",
            "score": 0.5556,
            "n": 99
          },
          {
            "key": "Sneasler",
            "score": 0.5551,
            "n": 245
          },
          {
            "key": "Scrafty-Mega",
            "score": 0.5263,
            "n": 57
          },
          {
            "key": "Rotom-Wash",
            "score": 0.5217,
            "n": 92
          },
          {
            "key": "Hydreigon",
            "score": 0.5085,
            "n": 59
          }
        ]
      },
      "1760": {
        "usage": 0.0018265999999999998,
        "raw_count": 8844,
        "viability_ceiling": [
          964,
          74,
          69,
          58
        ],
        "top_items": [
          {
            "key": "choicescarf",
            "weight": 13.218510889250462
          },
          {
            "key": "magnet",
            "weight": 1.8147837423568864
          },
          {
            "key": "nevermeltice",
            "weight": 1.1034380811322664
          },
          {
            "key": "leftovers",
            "weight": 0.9639123438971446
          },
          {
            "key": "sitrusberry",
            "weight": 0.35097296064753464
          },
          {
            "key": "focussash",
            "weight": 0.3308983154580652
          },
          {
            "key": "chopleberry",
            "weight": 0.33068337341607973
          },
          {
            "key": "lifeorb",
            "weight": 0.2398276251979392
          }
        ],
        "top_moves": [
          {
            "key": "blizzard",
            "weight": 18.818484017598834
          },
          {
            "key": "voltswitch",
            "weight": 12.53719070450795
          },
          {
            "key": "thunderbolt",
            "weight": 12.331244005105757
          },
          {
            "key": "electroweb",
            "weight": 7.904959459519388
          },
          {
            "key": "discharge",
            "weight": 6.587752942262177
          },
          {
            "key": "protect",
            "weight": 4.705549533875093
          },
          {
            "key": "trick",
            "weight": 3.60222102914351
          },
          {
            "key": "willowisp",
            "weight": 2.460944923510704
          }
        ],
        "top_abilities": [
          {
            "key": "levitate",
            "weight": 18.832768110104062
          }
        ],
        "top_spreads": [
          {
            "key": "Timid:2/0/0/32/0/32",
            "weight": 9.075951337575383
          },
          {
            "key": "Modest:2/0/0/32/0/32",
            "weight": 1.9686429450365512
          },
          {
            "key": "Modest:17/0/0/32/0/17",
            "weight": 1.4575736246740971
          },
          {
            "key": "Modest:2/0/32/32/0/0",
            "weight": 0.6424804664097824
          },
          {
            "key": "Modest:32/0/0/32/2/0",
            "weight": 0.5145964714897489
          },
          {
            "key": "Bold:13/0/12/32/9/0",
            "weight": 0.4451891299254675
          },
          {
            "key": "Calm:32/0/0/2/32/0",
            "weight": 0.44208096780010114
          },
          {
            "key": "Modest:0/0/0/32/2/32",
            "weight": 0.4049447130932033
          }
        ],
        "top_teammates": [
          {
            "key": "Froslass-Mega",
            "weight": 11.524959803343872
          },
          {
            "key": "Garchomp",
            "weight": 8.172917427607242
          },
          {
            "key": "Incineroar",
            "weight": 6.280060639822055
          },
          {
            "key": "Sneasler",
            "weight": 4.364696992849321
          },
          {
            "key": "Kingambit",
            "weight": 4.3549108824623355
          },
          {
            "key": "Talonflame",
            "weight": 3.2466462608997038
          },
          {
            "key": "Ninetales-Alola",
            "weight": 2.9600004532475297
          },
          {
            "key": "Aerodactyl",
            "weight": 2.5092825251046085
          }
        ],
        "top_counters": []
      }
    }
  },
  "image_url": "https://championsbattledata.com/pokemon_champions_assets/pokemon/Rotom.png",
  "battle_data": {
    "present": true,
    "source": "championsbattledata.com",
    "season": "Current",
    "format": "Doubles",
    "top_moves": [
      {
        "name": "Blizzard",
        "pct": 97.9,
        "rank": 1
      },
      {
        "name": "Thunderbolt",
        "pct": 63.4,
        "rank": 2
      },
      {
        "name": "Volt Switch",
        "pct": 56.7,
        "rank": 3
      },
      {
        "name": "Electroweb",
        "pct": 37.4,
        "rank": 4
      },
      {
        "name": "Protect",
        "pct": 31.6,
        "rank": 5
      },
      {
        "name": "Discharge",
        "pct": 22.0,
        "rank": 6
      },
      {
        "name": "Will-O-Wisp",
        "pct": 20.0,
        "rank": 7
      },
      {
        "name": "Trick",
        "pct": 19.2,
        "rank": 8
      },
      {
        "name": "Helping Hand",
        "pct": 8.0,
        "rank": 9
      },
      {
        "name": "Dark Pulse",
        "pct": 7.4,
        "rank": 10
      }
    ],
    "top_items": [
      {
        "name": "Choice Scarf",
        "pct": 52.0,
        "rank": 1
      },
      {
        "name": "Never-Melt Ice",
        "pct": 11.6,
        "rank": 2
      },
      {
        "name": "Leftovers",
        "pct": 6.9,
        "rank": 3
      },
      {
        "name": "Sitrus Berry",
        "pct": 6.1,
        "rank": 4
      },
      {
        "name": "Quick Claw",
        "pct": 3.7,
        "rank": 5
      },
      {
        "name": "Life Orb",
        "pct": 3.4,
        "rank": 6
      },
      {
        "name": "Wide Lens",
        "pct": 3.0,
        "rank": 7
      },
      {
        "name": "Focus Sash",
        "pct": 3.0,
        "rank": 8
      },
      {
        "name": "Magnet",
        "pct": 2.4,
        "rank": 9
      },
      {
        "name": "Bright Powder",
        "pct": 1.8,
        "rank": 10
      }
    ],
    "top_abilities": [
      {
        "name": "Levitate",
        "pct": 100.0,
        "rank": 1
      }
    ],
    "top_natures": [
      {
        "name": "Modest",
        "pct": 52.1,
        "stat_up": "Sp. Atk",
        "stat_down": "Attack",
        "rank": 1
      },
      {
        "name": "Timid",
        "pct": 39.4,
        "stat_up": "Speed",
        "stat_down": "Attack",
        "rank": 2
      },
      {
        "name": "Calm",
        "pct": 2.3,
        "stat_up": "Sp. Def",
        "stat_down": "Attack",
        "rank": 3
      },
      {
        "name": "Quiet",
        "pct": 2.2,
        "stat_up": "Sp. Atk",
        "stat_down": "Speed",
        "rank": 4
      },
      {
        "name": "Bold",
        "pct": 2.2,
        "stat_up": "Defense",
        "stat_down": "Attack",
        "rank": 5
      },
      {
        "name": "Relaxed",
        "pct": 0.5,
        "stat_up": "Defense",
        "stat_down": "Speed",
        "rank": 6
      },
      {
        "name": "Mild",
        "pct": 0.4,
        "stat_up": "Sp. Atk",
        "stat_down": "Defense",
        "rank": 7
      },
      {
        "name": "Sassy",
        "pct": 0.2,
        "stat_up": "Sp. Def",
        "stat_down": "Speed",
        "rank": 8
      },
      {
        "name": "Jolly",
        "pct": 0.2,
        "stat_up": "Speed",
        "stat_down": "Sp. Atk",
        "rank": 9
      },
      {
        "name": "Brave",
        "pct": 0.2,
        "stat_up": "Attack",
        "stat_down": "Speed",
        "rank": 10
      }
    ],
    "top_spreads": [
      {
        "sp": {
          "hp": 2,
          "atk": 0,
          "def": 0,
          "spa": 32,
          "spd": 0,
          "spe": 32
        },
        "pct": 42.1,
        "rank": 1
      },
      {
        "sp": {
          "hp": 0,
          "atk": 0,
          "def": 2,
          "spa": 32,
          "spd": 0,
          "spe": 32
        },
        "pct": 7.6,
        "rank": 2
      },
      {
        "sp": {
          "hp": 0,
          "atk": 0,
          "def": 0,
          "spa": 32,
          "spd": 2,
          "spe": 32
        },
        "pct": 6.7,
        "rank": 3
      },
      {
        "sp": {
          "hp": 32,
          "atk": 0,
          "def": 9,
          "spa": 25,
          "spd": 0,
          "spe": 0
        },
        "pct": 4.2,
        "rank": 4
      },
      {
        "sp": {
          "hp": 32,
          "atk": 0,
          "def": 2,
          "spa": 32,
          "spd": 0,
          "spe": 0
        },
        "pct": 3.6,
        "rank": 5
      },
      {
        "sp": {
          "hp": 0,
          "atk": 0,
          "def": 2,
          "spa": 32,
          "spd": 32,
          "spe": 0
        },
        "pct": 1.6,
        "rank": 6
      },
      {
        "sp": {
          "hp": 32,
          "atk": 0,
          "def": 0,
          "spa": 32,
          "spd": 2,
          "spe": 0
        },
        "pct": 1.6,
        "rank": 7
      },
      {
        "sp": {
          "hp": 0,
          "atk": 0,
          "def": 0,
          "spa": 32,
          "spd": 0,
          "spe": 32
        },
        "pct": 1.5,
        "rank": 8
      }
    ],
    "top_teammates": [
      {
        "name": "Froslass",
        "rank": 1
      },
      {
        "name": "Garchomp",
        "rank": 2
      },
      {
        "name": "Sneasler",
        "rank": 3
      },
      {
        "name": "Kingambit",
        "rank": 4
      },
      {
        "name": "Incineroar",
        "rank": 5
      },
      {
        "name": "Whimsicott",
        "rank": 6
      },
      {
        "name": "Alolan Ninetales",
        "rank": 7
      },
      {
        "name": "Basculegion Male",
        "rank": 8
      },
      {
        "name": "Talonflame",
        "rank": 9
      },
      {
        "name": "Sinistcha",
        "rank": 10
      }
    ]
  }
}